kiara_plugin/onboarding/__init__.py
kiara_plugin/onboarding/data_types.py
kiara_plugin/onboarding/py.typed
kiara_plugin/onboarding/version.txt
kiara_plugin/onboarding/models/__init__.py
kiara_plugin/onboarding/modules/__init__.py
kiara_plugin/onboarding/modules/download/__init__.py
kiara_plugin/onboarding/modules/download/github.py
kiara_plugin/onboarding/modules/download/zenodo.py
kiara_plugin/onboarding/modules/files/__init__.py
kiara_plugin/onboarding/modules/files/import_file.py
kiara_plugin/onboarding/modules/files/import_file_bundle.py
kiara_plugin/onboarding/pipelines/.gitkeep
kiara_plugin/onboarding/pipelines/__init__.py
kiara_plugin/onboarding/resources/.gitkeep
kiara_plugin/onboarding/utils/__init__.py
kiara_plugin/onboarding/utils/download.py
kiara_plugin_onboarding-0.5.3.dist-info/METADATA
kiara_plugin_onboarding-0.5.3.dist-info/WHEEL
kiara_plugin_onboarding-0.5.3.dist-info/entry_points.txt
kiara_plugin_onboarding-0.5.3.dist-info/licenses/AUTHORS.md
kiara_plugin_onboarding-0.5.3.dist-info/licenses/LICENSE
kiara_plugin_onboarding-0.5.3.dist-info/RECORD
