Metadata-Version: 2.4
Name: kiara_plugin.onboarding
Version: 0.5.3
Summary: kiara modules for data onboarding.
Project-URL: homepage, https://github.com/DHARPA-Project/kiara_plugin.onboarding
Project-URL: documentation, https://DHARPA-Project.github.io/kiara_plugin.onboarding
Project-URL: repository, https://github.com/DHARPA-Project/kiara_plugin.onboarding
Author-email: Markus Binsteiner <markus@frkl.dev>
License: MPL-2.0
License-File: AUTHORS.md
License-File: LICENSE
Keywords: kiara,kiara-plugin
Classifier: Development Status :: 3 - Alpha
Classifier: License :: OSI Approved :: Mozilla Public License 2.0 (MPL 2.0)
Classifier: Programming Language :: Python
Classifier: Programming Language :: Python :: 3
Classifier: Programming Language :: Python :: 3 :: Only
Classifier: Programming Language :: Python :: 3.9
Classifier: Programming Language :: Python :: 3.10
Classifier: Programming Language :: Python :: 3.11
Classifier: Programming Language :: Python :: 3.12
Classifier: Programming Language :: Python :: 3.13
Requires-Python: >=3.9
Requires-Dist: httpx>=0.23.0
Requires-Dist: kiara-plugin-core-types<0.6.0,>=0.5.2
Requires-Dist: kiara<0.6.0,>=0.5.15
Requires-Dist: pygithub>=1.58.0
Requires-Dist: pyzenodo3>=1.0.2
Requires-Dist: pyzotero>=1.5.9
Provides-Extra: jupyter
Requires-Dist: kiara[jupyter]; extra == 'jupyter'
Provides-Extra: marimo
Requires-Dist: kiara[marimo]; extra == 'marimo'
